{
  "dataset_revision": "3b6ea595c94bac3448a2ad167ca2e06abd340d6e",
  "task_name": "WikipediaRetrievalMultilingual",
  "mteb_version": "1.34.14",
  "scores": {
    "test": [
      {
        "ndcg_at_1": 0.78933,
        "ndcg_at_3": 0.86178,
        "ndcg_at_5": 0.87312,
        "ndcg_at_10": 0.88308,
        "ndcg_at_20": 0.88619,
        "ndcg_at_100": 0.88798,
        "ndcg_at_1000": 0.88894,
        "map_at_1": 0.78933,
        "map_at_3": 0.84478,
        "map_at_5": 0.85111,
        "map_at_10": 0.85537,
        "map_at_20": 0.85627,
        "map_at_100": 0.85654,
        "map_at_1000": 0.85658,
        "recall_at_1": 0.78933,
        "recall_at_3": 0.91067,
        "recall_at_5": 0.938,
        "recall_at_10": 0.968,
        "recall_at_20": 0.98,
        "recall_at_100": 0.98933,
        "recall_at_1000": 0.99667,
        "precision_at_1": 0.78933,
        "precision_at_3": 0.30356,
        "precision_at_5": 0.1876,
        "precision_at_10": 0.0968,
        "precision_at_20": 0.049,
        "precision_at_100": 0.00989,
        "precision_at_1000": 0.001,
        "mrr_at_1": 0.788667,
        "mrr_at_3": 0.844444,
        "mrr_at_5": 0.850778,
        "mrr_at_10": 0.855042,
        "mrr_at_20": 0.855939,
        "mrr_at_100": 0.856208,
        "mrr_at_1000": 0.856249,
        "nauc_ndcg_at_1_max": 0.491354,
        "nauc_ndcg_at_1_std": -0.223971,
        "nauc_ndcg_at_1_diff1": 0.786244,
        "nauc_ndcg_at_3_max": 0.535783,
        "nauc_ndcg_at_3_std": -0.198517,
        "nauc_ndcg_at_3_diff1": 0.757865,
        "nauc_ndcg_at_5_max": 0.529936,
        "nauc_ndcg_at_5_std": -0.197586,
        "nauc_ndcg_at_5_diff1": 0.758927,
        "nauc_ndcg_at_10_max": 0.535479,
        "nauc_ndcg_at_10_std": -0.190123,
        "nauc_ndcg_at_10_diff1": 0.763716,
        "nauc_ndcg_at_20_max": 0.531823,
        "nauc_ndcg_at_20_std": -0.190609,
        "nauc_ndcg_at_20_diff1": 0.762585,
        "nauc_ndcg_at_100_max": 0.529149,
        "nauc_ndcg_at_100_std": -0.196448,
        "nauc_ndcg_at_100_diff1": 0.764003,
        "nauc_ndcg_at_1000_max": 0.528745,
        "nauc_ndcg_at_1000_std": -0.197034,
        "nauc_ndcg_at_1000_diff1": 0.766406,
        "nauc_map_at_1_max": 0.491354,
        "nauc_map_at_1_std": -0.223971,
        "nauc_map_at_1_diff1": 0.786244,
        "nauc_map_at_3_max": 0.523241,
        "nauc_map_at_3_std": -0.205965,
        "nauc_map_at_3_diff1": 0.76588,
        "nauc_map_at_5_max": 0.520379,
        "nauc_map_at_5_std": -0.205185,
        "nauc_map_at_5_diff1": 0.766967,
        "nauc_map_at_10_max": 0.522546,
        "nauc_map_at_10_std": -0.201831,
        "nauc_map_at_10_diff1": 0.768724,
        "nauc_map_at_20_max": 0.521894,
        "nauc_map_at_20_std": -0.20134,
        "nauc_map_at_20_diff1": 0.768526,
        "nauc_map_at_100_max": 0.521589,
        "nauc_map_at_100_std": -0.202036,
        "nauc_map_at_100_diff1": 0.768719,
        "nauc_map_at_1000_max": 0.521616,
        "nauc_map_at_1000_std": -0.20201,
        "nauc_map_at_1000_diff1": 0.768836,
        "nauc_recall_at_1_max": 0.491354,
        "nauc_recall_at_1_std": -0.223971,
        "nauc_recall_at_1_diff1": 0.786244,
        "nauc_recall_at_3_max": 0.594109,
        "nauc_recall_at_3_std": -0.163677,
        "nauc_recall_at_3_diff1": 0.720592,
        "nauc_recall_at_5_max": 0.587603,
        "nauc_recall_at_5_std": -0.150226,
        "nauc_recall_at_5_diff1": 0.707112,
        "nauc_recall_at_10_max": 0.687422,
        "nauc_recall_at_10_std": -0.049837,
        "nauc_recall_at_10_diff1": 0.711815,
        "nauc_recall_at_20_max": 0.689605,
        "nauc_recall_at_20_std": -0.00901,
        "nauc_recall_at_20_diff1": 0.655991,
        "nauc_recall_at_100_max": 0.686537,
        "nauc_recall_at_100_std": -0.150589,
        "nauc_recall_at_100_diff1": 0.635767,
        "nauc_recall_at_1000_max": 0.858543,
        "nauc_recall_at_1000_std": -0.266853,
        "nauc_recall_at_1000_diff1": 0.862745,
        "nauc_precision_at_1_max": 0.491354,
        "nauc_precision_at_1_std": -0.223971,
        "nauc_precision_at_1_diff1": 0.786244,
        "nauc_precision_at_3_max": 0.594109,
        "nauc_precision_at_3_std": -0.163677,
        "nauc_precision_at_3_diff1": 0.720592,
        "nauc_precision_at_5_max": 0.587603,
        "nauc_precision_at_5_std": -0.150226,
        "nauc_precision_at_5_diff1": 0.707112,
        "nauc_precision_at_10_max": 0.687422,
        "nauc_precision_at_10_std": -0.049837,
        "nauc_precision_at_10_diff1": 0.711815,
        "nauc_precision_at_20_max": 0.689605,
        "nauc_precision_at_20_std": -0.00901,
        "nauc_precision_at_20_diff1": 0.655991,
        "nauc_precision_at_100_max": 0.686537,
        "nauc_precision_at_100_std": -0.150589,
        "nauc_precision_at_100_diff1": 0.635767,
        "nauc_precision_at_1000_max": 0.858543,
        "nauc_precision_at_1000_std": -0.266853,
        "nauc_precision_at_1000_diff1": 0.862745,
        "nauc_mrr_at_1_max": 0.493111,
        "nauc_mrr_at_1_std": -0.220449,
        "nauc_mrr_at_1_diff1": 0.78772,
        "nauc_mrr_at_3_max": 0.524356,
        "nauc_mrr_at_3_std": -0.203656,
        "nauc_mrr_at_3_diff1": 0.766893,
        "nauc_mrr_at_5_max": 0.521549,
        "nauc_mrr_at_5_std": -0.202774,
        "nauc_mrr_at_5_diff1": 0.768024,
        "nauc_mrr_at_10_max": 0.523748,
        "nauc_mrr_at_10_std": -0.19935,
        "nauc_mrr_at_10_diff1": 0.769811,
        "nauc_mrr_at_20_max": 0.523106,
        "nauc_mrr_at_20_std": -0.198844,
        "nauc_mrr_at_20_diff1": 0.769621,
        "nauc_mrr_at_100_max": 0.522803,
        "nauc_mrr_at_100_std": -0.199534,
        "nauc_mrr_at_100_diff1": 0.769815,
        "nauc_mrr_at_1000_max": 0.522831,
        "nauc_mrr_at_1000_std": -0.199506,
        "nauc_mrr_at_1000_diff1": 0.769932,
        "main_score": 0.88308,
        "hf_subset": "fa",
        "languages": [
          "fas-Arab"
        ]
      }
    ]
  },
  "evaluation_time": 21.88571572303772,
  "kg_co2_emissions": null
}