{
  "dataset_revision": "45d9176b6fcba33abc58494ee82f18ee7e8ddbae",
  "task_name": "ClimateFEVER-Fa",
  "mteb_version": "1.34.14",
  "scores": {
    "test": [
      {
        "ndcg_at_1": 0.13225,
        "ndcg_at_3": 0.11209,
        "ndcg_at_5": 0.12013,
        "ndcg_at_10": 0.13703,
        "ndcg_at_20": 0.15425,
        "ndcg_at_100": 0.19179,
        "ndcg_at_1000": 0.22997,
        "map_at_1": 0.06124,
        "map_at_3": 0.08117,
        "map_at_5": 0.0875,
        "map_at_10": 0.09399,
        "map_at_20": 0.0986,
        "map_at_100": 0.10423,
        "map_at_1000": 0.10581,
        "recall_at_1": 0.06124,
        "recall_at_3": 0.10371,
        "recall_at_5": 0.12617,
        "recall_at_10": 0.16455,
        "recall_at_20": 0.2155,
        "recall_at_100": 0.36351,
        "recall_at_1000": 0.58875,
        "precision_at_1": 0.13225,
        "precision_at_3": 0.07904,
        "precision_at_5": 0.06085,
        "precision_at_10": 0.04143,
        "precision_at_20": 0.02769,
        "precision_at_100": 0.01,
        "precision_at_1000": 0.00168,
        "mrr_at_1": 0.132248,
        "mrr_at_3": 0.173507,
        "mrr_at_5": 0.18481,
        "mrr_at_10": 0.19487,
        "mrr_at_20": 0.201089,
        "mrr_at_100": 0.206248,
        "mrr_at_1000": 0.207144,
        "nauc_ndcg_at_1_max": 0.353767,
        "nauc_ndcg_at_1_std": 0.196086,
        "nauc_ndcg_at_1_diff1": 0.301468,
        "nauc_ndcg_at_3_max": 0.330623,
        "nauc_ndcg_at_3_std": 0.16419,
        "nauc_ndcg_at_3_diff1": 0.232869,
        "nauc_ndcg_at_5_max": 0.342697,
        "nauc_ndcg_at_5_std": 0.159377,
        "nauc_ndcg_at_5_diff1": 0.236536,
        "nauc_ndcg_at_10_max": 0.347792,
        "nauc_ndcg_at_10_std": 0.176004,
        "nauc_ndcg_at_10_diff1": 0.22939,
        "nauc_ndcg_at_20_max": 0.356491,
        "nauc_ndcg_at_20_std": 0.19703,
        "nauc_ndcg_at_20_diff1": 0.222129,
        "nauc_ndcg_at_100_max": 0.365334,
        "nauc_ndcg_at_100_std": 0.237667,
        "nauc_ndcg_at_100_diff1": 0.205913,
        "nauc_ndcg_at_1000_max": 0.368955,
        "nauc_ndcg_at_1000_std": 0.265993,
        "nauc_ndcg_at_1000_diff1": 0.202575,
        "nauc_map_at_1_max": 0.352574,
        "nauc_map_at_1_std": 0.158989,
        "nauc_map_at_1_diff1": 0.306945,
        "nauc_map_at_3_max": 0.332495,
        "nauc_map_at_3_std": 0.140856,
        "nauc_map_at_3_diff1": 0.253886,
        "nauc_map_at_5_max": 0.341599,
        "nauc_map_at_5_std": 0.142999,
        "nauc_map_at_5_diff1": 0.255505,
        "nauc_map_at_10_max": 0.344907,
        "nauc_map_at_10_std": 0.152471,
        "nauc_map_at_10_diff1": 0.251445,
        "nauc_map_at_20_max": 0.348695,
        "nauc_map_at_20_std": 0.160906,
        "nauc_map_at_20_diff1": 0.247802,
        "nauc_map_at_100_max": 0.350616,
        "nauc_map_at_100_std": 0.171082,
        "nauc_map_at_100_diff1": 0.243054,
        "nauc_map_at_1000_max": 0.351547,
        "nauc_map_at_1000_std": 0.173952,
        "nauc_map_at_1000_diff1": 0.242853,
        "nauc_recall_at_1_max": 0.352574,
        "nauc_recall_at_1_std": 0.158989,
        "nauc_recall_at_1_diff1": 0.306945,
        "nauc_recall_at_3_max": 0.312764,
        "nauc_recall_at_3_std": 0.133209,
        "nauc_recall_at_3_diff1": 0.202426,
        "nauc_recall_at_5_max": 0.328692,
        "nauc_recall_at_5_std": 0.13474,
        "nauc_recall_at_5_diff1": 0.201485,
        "nauc_recall_at_10_max": 0.326977,
        "nauc_recall_at_10_std": 0.164472,
        "nauc_recall_at_10_diff1": 0.182501,
        "nauc_recall_at_20_max": 0.325134,
        "nauc_recall_at_20_std": 0.200299,
        "nauc_recall_at_20_diff1": 0.156359,
        "nauc_recall_at_100_max": 0.317065,
        "nauc_recall_at_100_std": 0.281288,
        "nauc_recall_at_100_diff1": 0.103537,
        "nauc_recall_at_1000_max": 0.294941,
        "nauc_recall_at_1000_std": 0.361297,
        "nauc_recall_at_1000_diff1": 0.07209,
        "nauc_precision_at_1_max": 0.353767,
        "nauc_precision_at_1_std": 0.196086,
        "nauc_precision_at_1_diff1": 0.301468,
        "nauc_precision_at_3_max": 0.317278,
        "nauc_precision_at_3_std": 0.178894,
        "nauc_precision_at_3_diff1": 0.196767,
        "nauc_precision_at_5_max": 0.34265,
        "nauc_precision_at_5_std": 0.189744,
        "nauc_precision_at_5_diff1": 0.195388,
        "nauc_precision_at_10_max": 0.340899,
        "nauc_precision_at_10_std": 0.220524,
        "nauc_precision_at_10_diff1": 0.177395,
        "nauc_precision_at_20_max": 0.343741,
        "nauc_precision_at_20_std": 0.26311,
        "nauc_precision_at_20_diff1": 0.154273,
        "nauc_precision_at_100_max": 0.32035,
        "nauc_precision_at_100_std": 0.343307,
        "nauc_precision_at_100_diff1": 0.086408,
        "nauc_precision_at_1000_max": 0.253669,
        "nauc_precision_at_1000_std": 0.389731,
        "nauc_precision_at_1000_diff1": 0.039802,
        "nauc_mrr_at_1_max": 0.353767,
        "nauc_mrr_at_1_std": 0.196086,
        "nauc_mrr_at_1_diff1": 0.301468,
        "nauc_mrr_at_3_max": 0.334964,
        "nauc_mrr_at_3_std": 0.191505,
        "nauc_mrr_at_3_diff1": 0.242761,
        "nauc_mrr_at_5_max": 0.341505,
        "nauc_mrr_at_5_std": 0.195095,
        "nauc_mrr_at_5_diff1": 0.239581,
        "nauc_mrr_at_10_max": 0.343967,
        "nauc_mrr_at_10_std": 0.200935,
        "nauc_mrr_at_10_diff1": 0.237139,
        "nauc_mrr_at_20_max": 0.346553,
        "nauc_mrr_at_20_std": 0.206346,
        "nauc_mrr_at_20_diff1": 0.236208,
        "nauc_mrr_at_100_max": 0.346857,
        "nauc_mrr_at_100_std": 0.208245,
        "nauc_mrr_at_100_diff1": 0.236571,
        "nauc_mrr_at_1000_max": 0.346798,
        "nauc_mrr_at_1000_std": 0.20832,
        "nauc_mrr_at_1000_diff1": 0.236344,
        "main_score": 0.13703,
        "hf_subset": "default",
        "languages": [
          "fas-Arab"
        ]
      }
    ]
  },
  "evaluation_time": 12049.437308073044,
  "kg_co2_emissions": null
}